LICENSE
send2any/__init__.py
send2any/cli.py
send2any/conf.py
send2any/slack.py
send2any-0.1.0.dist-info/LICENSE
send2any-0.1.0.dist-info/WHEEL
send2any-0.1.0.dist-info/METADATA
send2any-0.1.0.dist-info/RECORD
