Metadata-Version: 2.1
Name: send2any
Version: 0.1.0
Summary: An unified notification sender sdk
Home-page: https://github.com/nuxion/sent2any
License: Apache-2.0
Keywords: discord,slack,email,smtp
Author: nuxion
Author-email: nuxion@gmail.com
Requires-Python: >=3.8,<3.10
Classifier: License :: OSI Approved :: Apache Software License
Classifier: Operating System :: POSIX :: Linux
Classifier: Programming Language :: Python :: 3
Classifier: Programming Language :: Python :: 3.8
Classifier: Programming Language :: Python :: 3.9
Requires-Dist: httpx (>=0.22.0,<0.23.0)
Project-URL: Documentation, https://sent2any.readthedocs.io/
Project-URL: Repository, https://github.com/nuxion/sent2any
